streamdeckd/__init__.py
streamdeckd/__main__.py
streamdeckd/application.py
streamdeckd/devices.py
streamdeckd/display.py
streamdeckd/registry.py
streamdeckd/scheduler.py
streamdeckd/signals.py
streamdeckd/state.py
streamdeckd/utils.py
streamdeckd/variables.py
streamdeckd/commands/enumerate.py
streamdeckd/commands/run.py
streamdeckd/config/__init__.py
streamdeckd/config/action.py
streamdeckd/config/application.py
streamdeckd/config/base.py
streamdeckd/config/state.py
streamdeckd/config/streamdeck.py
streamdeckd/config/validators.py
streamdeckd_ext/http.py
streamdeckd_ext/pulseaudio.py
streamdeckd_ext/run.py
streamdeckd_ext/strings.py
streamdeckd_ext/system.py
streamdeckd_ext/template.py
streamdeckd_ext/time.py
streamdeckd-0.1.0.dist-info/COPYING
streamdeckd-0.1.0.dist-info/COPYING.LESSER
streamdeckd-0.1.0.dist-info/METADATA
streamdeckd-0.1.0.dist-info/WHEEL
streamdeckd-0.1.0.dist-info/entry_points.txt
streamdeckd-0.1.0.dist-info/top_level.txt
streamdeckd-0.1.0.dist-info/RECORD
