Metadata-Version: 2.1
Name: streamdeckd
Version: 0.1.0
Summary: StreamDeck Daemon
Home-page: UNKNOWN
Author: stuxcrystal
License: UNKNOWN
Platform: UNKNOWN
Requires-Dist: aiorun
Requires-Dist: crossplane
Requires-Dist: pillow
Requires-Dist: streamdeck
Provides-Extra: all
Requires-Dist: aiohttp ; extra == 'all'
Requires-Dist: jsonpath-ng ; extra == 'all'
Requires-Dist: pulsectl ; extra == 'all'
Provides-Extra: http
Requires-Dist: aiohttp ; extra == 'http'
Requires-Dist: jsonpath-ng ; extra == 'http'
Provides-Extra: pulseaudio
Requires-Dist: pulsectl ; extra == 'pulseaudio'
